[{"type": "Cyclist", "occluded_state": 1, "truncated_state": 0, "alpha": -0.13069477871606988, "2d_box": {"xmin": 1087.438232, "ymin": 493.640594, "xmax": 1181.555786, "ymax": 562.7361450000001}, "3d_dimensions": {"h": 0.966279, "w": 0.431923, "l": 1.418936}, "3d_location": {"x": 59.67261, "y": -2.166908, "z": -1.37592}, "rotation": -1.471782}, {"type": "Car", "occluded_state": 1, "truncated_state": 0, "alpha": -1.5376166854952367, "2d_box": {"xmin": 860.180542, "ymin": 491.174561, "xmax": 901.041931, "ymax": 524.771668}, "3d_dimensions": {"h": 1.739788, "w": 1.728007, "l": 4.302729}, "3d_location": {"x": 184.9672, "y": 6.451345, "z": -1.482637}, "rotation": 0.003352844}, {"type": "Car", "occluded_state": 0, "truncated_state": 0, "alpha": -1.5234670817804157, "2d_box": {"xmin": 773.057007, "ymin": 489.328064, "xmax": 814.283386, "ymax": 523.263733}, "3d_dimensions": {"h": 1.650633, "w": 2.077043, "l": 4.213441}, "3d_location": {"x": 199.3867, "y": 11.47302, "z": -1.61253}, "rotation": 0.01174974}, {"type": "Truck", "occluded_state": 1, "truncated_state": 0, "alpha": -1.5249300612738779, "2d_box": {"xmin": 848.117859, "ymin": 459.361969, "xmax": 897.45398, "ymax": 523.174927}, "3d_dimensions": {"h": 2.391879, "w": 2.973861, "l": 6.78762}, "3d_location": {"x": 193.9683, "y": 7.31209, "z": -0.8132067}, "rotation": -0.006585184}, {"type": "Pedestrian", "occluded_state": 1, "truncated_state": 0, "alpha": 0, "2d_box": {"xmin": 651.9333256991, "ymin": 488.3329642464, "xmax": 663.4538244778, "ymax": 518.5800790112}, "3d_dimensions": {"h": 0, "w": 0, "l": 0}, "3d_location": {"x": 0.0, "y": 0.0, "z": 0.0}, "rotation": 0.0}, {"type": "Tricyclist", "occluded_state": 1, "truncated_state": 0, "alpha": 0, "2d_box": {"xmin": 682.6778291591, "ymin": 489.0609324737, "xmax": 705.4122862101001, "ymax": 517.7063483579}, "3d_dimensions": {"h": 0, "w": 0, "l": 0}, "3d_location": {"x": 0.0, "y": 0.0, "z": 0.0}, "rotation": 0.0}, {"type": "Motorcyclist", "occluded_state": 0, "truncated_state": 0, "alpha": 0, "2d_box": {"xmin": 739.9305882901, "ymin": 483.9749616179, "xmax": 757.3918638096, "ymax": 519.5200124036}, "3d_dimensions": {"h": 0, "w": 0, "l": 0}, "3d_location": {"x": 0.0, "y": 0.0, "z": 0.0}, "rotation": 0.0}, {"type": "Motorcyclist", "occluded_state": 0, "truncated_state": 0, "alpha": 0, "2d_box": {"xmin": 819.6383949636, "ymin": 490.4998148086, "xmax": 832.7334422249, "ymax": 520.6184235096}, "3d_dimensions": {"h": 0, "w": 0, "l": 0}, "3d_location": {"x": 0.0, "y": 0.0, "z": 0.0}, "rotation": 0.0}, {"type": "Tricyclist", "occluded_state": 2, "truncated_state": 0, "alpha": 0, "2d_box": {"xmin": 905.784742141, "ymin": 486.7630703223, "xmax": 935.2843673581, "ymax": 514.1878984679}, "3d_dimensions": {"h": 0, "w": 0, "l": 0}, "3d_location": {"x": 0.0, "y": 0.0, "z": 0.0}, "rotation": 0.0}, {"type": "Truck", "occluded_state": 2, "truncated_state": 0, "alpha": 0, "2d_box": {"xmin": 819.0775195112, "ymin": 460.7500366887, "xmax": 876.0302895394, "ymax": 519.4753523142}, "3d_dimensions": {"h": 0, "w": 0, "l": 0}, "3d_location": {"x": 0.0, "y": 0.0, "z": 0.0}, "rotation": 0.0}, {"type": "Car", "occluded_state": 1, "truncated_state": 0, "alpha": 0, "2d_box": {"xmin": 754.5270119859, "ymin": 490.237260217, "xmax": 784.8488558205, "ymax": 512.1967248876}, "3d_dimensions": {"h": 0, "w": 0, "l": 0}, "3d_location": {"x": 0.0, "y": 0.0, "z": 0.0}, "rotation": 0.0}, {"type": "Trafficcone", "occluded_state": 0, "truncated_state": 0, "alpha": 0, "2d_box": {"xmin": 887.2169142771, "ymin": 511.3464198188, "xmax": 903.2219720409, "ymax": 542.0834057516}, "3d_dimensions": {"h": 0, "w": 0, "l": 0}, "3d_location": {"x": 0.0, "y": 0.0, "z": 0.0}, "rotation": 0.0}, {"type": "Car", "occluded_state": 2, "truncated_state": 0, "alpha": 0, "2d_box": {"xmin": 803.7299861512, "ymin": 484.3136793402, "xmax": 827.3485609763001, "ymax": 502.501244981}, "3d_dimensions": {"h": 0, "w": 0, "l": 0}, "3d_location": {"x": 0.0, "y": 0.0, "z": 0.0}, "rotation": 0.0}]